txt2dataset/__init__.py
txt2dataset/dataset_builder.py
txt2dataset-0.4.1.dist-info/METADATA
txt2dataset-0.4.1.dist-info/WHEEL
txt2dataset-0.4.1.dist-info/top_level.txt
txt2dataset-0.4.1.dist-info/RECORD
