Metadata-Version: 2.1
Name: txt2dataset
Version: 0.4.1
Summary: Convert text to datasets
Requires-Dist: google-genai
Requires-Dist: tqdm
